WeiruanGuanfangVbZhinan20171224/README.md
WeiruanGuanfangVbZhinan20171224/__init__.py
WeiruanGuanfangVbZhinan20171224/__main__.py
WeiruanGuanfangVbZhinan20171224/file.epub
WeiruanGuanfangVbZhinan20171224/index.html
WeiruanGuanfangVbZhinan20171224/css/__init__.py
WeiruanGuanfangVbZhinan20171224/css/annotations.css
WeiruanGuanfangVbZhinan20171224/css/main.css
WeiruanGuanfangVbZhinan20171224/css/normalize.css
WeiruanGuanfangVbZhinan20171224/css/popup.css
WeiruanGuanfangVbZhinan20171224/font/__init__.py
WeiruanGuanfangVbZhinan20171224/font/fontello.eot
WeiruanGuanfangVbZhinan20171224/font/fontello.svg
WeiruanGuanfangVbZhinan20171224/font/fontello.ttf
WeiruanGuanfangVbZhinan20171224/font/fontello.woff
WeiruanGuanfangVbZhinan20171224/img/__init__.py
WeiruanGuanfangVbZhinan20171224/img/annotator-glyph-sprite.png
WeiruanGuanfangVbZhinan20171224/img/annotator-icon-sprite.png
WeiruanGuanfangVbZhinan20171224/img/apple-touch-icon.png
WeiruanGuanfangVbZhinan20171224/img/cancelfullscreen.png
WeiruanGuanfangVbZhinan20171224/img/close.png
WeiruanGuanfangVbZhinan20171224/img/fullscreen.png
WeiruanGuanfangVbZhinan20171224/img/loader.gif
WeiruanGuanfangVbZhinan20171224/img/menu-icon.png
WeiruanGuanfangVbZhinan20171224/img/save.png
WeiruanGuanfangVbZhinan20171224/img/saved.png
WeiruanGuanfangVbZhinan20171224/img/settings-s.png
WeiruanGuanfangVbZhinan20171224/img/settings.png
WeiruanGuanfangVbZhinan20171224/img/star.png
WeiruanGuanfangVbZhinan20171224/js/__init__.py
WeiruanGuanfangVbZhinan20171224/js/epub.js
WeiruanGuanfangVbZhinan20171224/js/epub.min.js
WeiruanGuanfangVbZhinan20171224/js/epub.min.map
WeiruanGuanfangVbZhinan20171224/js/hooks.min.js
WeiruanGuanfangVbZhinan20171224/js/hooks.min.map
WeiruanGuanfangVbZhinan20171224/js/reader.js
WeiruanGuanfangVbZhinan20171224/js/reader.js.map
WeiruanGuanfangVbZhinan20171224/js/reader.min.js
WeiruanGuanfangVbZhinan20171224/js/reader.min.map
WeiruanGuanfangVbZhinan20171224/js/hooks/__init__.py
weiruan_guanfang_vb_zhinan_20171224-2024.3.2.0.dist-info/METADATA
weiruan_guanfang_vb_zhinan_20171224-2024.3.2.0.dist-info/WHEEL
weiruan_guanfang_vb_zhinan_20171224-2024.3.2.0.dist-info/entry_points.txt
weiruan_guanfang_vb_zhinan_20171224-2024.3.2.0.dist-info/top_level.txt
weiruan_guanfang_vb_zhinan_20171224-2024.3.2.0.dist-info/RECORD
